[
  {
    "date": "2025-03-03",
    "open": 817.96,
    "high": 839.26,
    "low": 816.44,
    "close": 830.55,
    "volume": 1013763,
    "trades": 2352,
    "vwap": 826.05
  },
  {
    "date": "2025-03-04",
    "open": 832.85,
    "high": 839.93,
    "low": 816.83,
    "close": 824.73,
    "volume": 999866,
    "trades": 865,
    "vwap": 828.58
  },
  {
    "date": "2025-03-05",
    "open": 825.34,
    "high": 834.07,
    "low": 809.48,
    "close": 811.83,
    "volume": 1317604,
    "trades": 3071,
    "vwap": 820.18
  },
  {
    "date": "2025-03-06",
    "open": 810.86,
    "high": 814.96,
    "low": 800.59,
    "close": 802.05,
    "volume": 1253111,
    "trades": 1515,
    "vwap": 807.12
  },
  {
    "date": "2025-03-07",
    "open": 797.59,
    "high": 823.58,
    "low": 786.01,
    "close": 822.63,
    "volume": 854345,
    "trades": 1787,
    "vwap": 807.45
  },
  {
    "date": "2025-03-10",
    "open": 822.76,
    "high": 839.2,
    "low": 814.45,
    "close": 831.67,
    "volume": 764921,
    "trades": 1176,
    "vwap": 827.02
  },
  {
    "date": "2025-03-11",
    "open": 827.24,
    "high": 842.23,
    "low": 824.65,
    "close": 838.73,
    "volume": 924459,
    "trades": 799,
    "vwap": 833.21
  },
  {
    "date": "2025-03-12",
    "open": 840.09,
    "high": 861.78,
    "low": 839.22,
    "close": 857.09,
    "volume": 388702,
    "trades": 918,
    "vwap": 849.55
  },
  {
    "date": "2025-03-13",
    "open": 855.26,
    "high": 874.04,
    "low": 847.04,
    "close": 871.68,
    "volume": 440883,
    "trades": 485,
    "vwap": 862.01
  },
  {
    "date": "2025-03-14",
    "open": 868.28,
    "high": 876.93,
    "low": 862.91,
    "close": 876.5,
    "volume": 544977,
    "trades": 928,
    "vwap": 871.15
  },
  {
    "date": "2025-03-17",
    "open": 876.27,
    "high": 893.33,
    "low": 870.82,
    "close": 890.56,
    "volume": 1020175,
    "trades": 1504,
    "vwap": 882.74
  },
  {
    "date": "2025-03-18",
    "open": 889.14,
    "high": 891.46,
    "low": 880.0,
    "close": 880.93,
    "volume": 1265172,
    "trades": 2714,
    "vwap": 885.38
  },
  {
    "date": "2025-03-19",
    "open": 881.94,
    "high": 895.79,
    "low": 877.4,
    "close": 888.7,
    "volume": 813305,
    "trades": 1017,
    "vwap": 885.96
  },
  {
    "date": "2025-03-20",
    "open": 887.76,
    "high": 894.32,
    "low": 878.15,
    "close": 893.23,
    "volume": 1107184,
    "trades": 2170,
    "vwap": 888.36
  },
  {
    "date": "2025-03-21",
    "open": 898.59,
    "high": 907.88,
    "low": 893.3,
    "close": 902.11,
    "volume": 670757,
    "trades": 1380,
    "vwap": 900.47
  },
  {
    "date": "2025-03-24",
    "open": 902.48,
    "high": 902.53,
    "low": 893.64,
    "close": 899.74,
    "volume": 999282,
    "trades": 1024,
    "vwap": 899.6
  },
  {
    "date": "2025-03-25",
    "open": 901.1,
    "high": 903.05,
    "low": 896.55,
    "close": 901.23,
    "volume": 746418,
    "trades": 927,
    "vwap": 900.48
  },
  {
    "date": "2025-03-26",
    "open": 892.79,
    "high": 899.27,
    "low": 855.2,
    "close": 861.18,
    "volume": 267681,
    "trades": 1129,
    "vwap": 877.11
  },
  {
    "date": "2025-03-27",
    "open": 859.67,
    "high": 861.45,
    "low": 841.93,
    "close": 845.23,
    "volume": 1229861,
    "trades": 1509,
    "vwap": 852.07
  },
  {
    "date": "2025-03-28",
    "open": 840.39,
    "high": 848.07,
    "low": 825.7,
    "close": 828.99,
    "volume": 1050699,
    "trades": 2269,
    "vwap": 835.79
  },
  {
    "date": "2025-03-31",
    "open": 823.36,
    "high": 824.3,
    "low": 803.5,
    "close": 804.54,
    "volume": 1413186,
    "trades": 3632,
    "vwap": 813.93
  },
  {
    "date": "2025-04-01",
    "open": 807.8,
    "high": 815.56,
    "low": 806.8,
    "close": 813.19,
    "volume": 643248,
    "trades": 575,
    "vwap": 810.84
  },
  {
    "date": "2025-04-02",
    "open": 807.78,
    "high": 812.16,
    "low": 795.2,
    "close": 796.07,
    "volume": 635892,
    "trades": 704,
    "vwap": 802.8
  },
  {
    "date": "2025-04-03",
    "open": 796.12,
    "high": 798.83,
    "low": 766.6,
    "close": 772.04,
    "volume": 487708,
    "trades": 1088,
    "vwap": 783.4
  },
  {
    "date": "2025-04-04",
    "open": 770.5,
    "high": 773.36,
    "low": 764.3,
    "close": 766.89,
    "volume": 1126724,
    "trades": 2183,
    "vwap": 768.76
  },
  {
    "date": "2025-04-07",
    "open": 766.83,
    "high": 769.47,
    "low": 759.08,
    "close": 763.75,
    "volume": 1130016,
    "trades": 2810,
    "vwap": 764.78
  },
  {
    "date": "2025-04-08",
    "open": 762.91,
    "high": 766.93,
    "low": 762.82,
    "close": 765.42,
    "volume": 766690,
    "trades": 710,
    "vwap": 764.52
  },
  {
    "date": "2025-04-09",
    "open": 770.06,
    "high": 783.23,
    "low": 765.13,
    "close": 778.64,
    "volume": 676800,
    "trades": 1829,
    "vwap": 774.27
  },
  {
    "date": "2025-04-10",
    "open": 779.32,
    "high": 789.42,
    "low": 774.68,
    "close": 777.63,
    "volume": 1588201,
    "trades": 5294,
    "vwap": 780.26
  },
  {
    "date": "2025-04-11",
    "open": 779.17,
    "high": 780.33,
    "low": 771.84,
    "close": 774.35,
    "volume": 824311,
    "trades": 797,
    "vwap": 776.42
  },
  {
    "date": "2025-04-14",
    "open": 775.38,
    "high": 777.72,
    "low": 768.66,
    "close": 777.3,
    "volume": 982610,
    "trades": 1069,
    "vwap": 774.77
  },
  {
    "date": "2025-04-15",
    "open": 779.01,
    "high": 779.56,
    "low": 776.32,
    "close": 779.16,
    "volume": 1449162,
    "trades": 4140,
    "vwap": 778.51
  },
  {
    "date": "2025-04-16",
    "open": 778.22,
    "high": 782.31,
    "low": 772.42,
    "close": 779.89,
    "volume": 1041053,
    "trades": 2949,
    "vwap": 778.21
  },
  {
    "date": "2025-04-17",
    "open": 779.08,
    "high": 793.87,
    "low": 776.44,
    "close": 791.63,
    "volume": 1058613,
    "trades": 1331,
    "vwap": 785.26
  },
  {
    "date": "2025-04-18",
    "open": 791.69,
    "high": 809.41,
    "low": 789.27,
    "close": 804.37,
    "volume": 1023993,
    "trades": 859,
    "vwap": 798.68
  },
  {
    "date": "2025-04-21",
    "open": 809.06,
    "high": 823.38,
    "low": 807.79,
    "close": 819.84,
    "volume": 500095,
    "trades": 510,
    "vwap": 815.02
  },
  {
    "date": "2025-04-22",
    "open": 813.27,
    "high": 820.5,
    "low": 795.08,
    "close": 799.55,
    "volume": 767921,
    "trades": 882,
    "vwap": 807.1
  },
  {
    "date": "2025-04-23",
    "open": 797.46,
    "high": 810.04,
    "low": 795.39,
    "close": 805.25,
    "volume": 863251,
    "trades": 812,
    "vwap": 802.03
  },
  {
    "date": "2025-04-24",
    "open": 808.28,
    "high": 814.23,
    "low": 808.22,
    "close": 813.21,
    "volume": 696602,
    "trades": 1882,
    "vwap": 810.98
  },
  {
    "date": "2025-04-25",
    "open": 817.22,
    "high": 826.58,
    "low": 813.36,
    "close": 821.66,
    "volume": 788032,
    "trades": 1965,
    "vwap": 819.71
  },
  {
    "date": "2025-04-28",
    "open": 816.57,
    "high": 820.52,
    "low": 807.85,
    "close": 808.68,
    "volume": 1187268,
    "trades": 1449,
    "vwap": 813.41
  },
  {
    "date": "2025-04-29",
    "open": 808.04,
    "high": 843.93,
    "low": 805.99,
    "close": 835.17,
    "volume": 877640,
    "trades": 854,
    "vwap": 823.29
  },
  {
    "date": "2025-04-30",
    "open": 836.21,
    "high": 844.53,
    "low": 832.57,
    "close": 841.43,
    "volume": 483640,
    "trades": 756,
    "vwap": 838.68
  },
  {
    "date": "2025-05-01",
    "open": 842.72,
    "high": 845.52,
    "low": 810.66,
    "close": 815.82,
    "volume": 443350,
    "trades": 978,
    "vwap": 828.68
  },
  {
    "date": "2025-05-02",
    "open": 815.89,
    "high": 828.08,
    "low": 807.97,
    "close": 826.7,
    "volume": 752889,
    "trades": 1214,
    "vwap": 819.66
  },
  {
    "date": "2025-05-05",
    "open": 826.5,
    "high": 833.62,
    "low": 804.85,
    "close": 813.44,
    "volume": 667632,
    "trades": 748,
    "vwap": 819.6
  },
  {
    "date": "2025-05-06",
    "open": 815.33,
    "high": 819.06,
    "low": 801.92,
    "close": 802.09,
    "volume": 598055,
    "trades": 534,
    "vwap": 809.6
  },
  {
    "date": "2025-05-07",
    "open": 804.78,
    "high": 812.43,
    "low": 802.37,
    "close": 812.2,
    "volume": 636826,
    "trades": 776,
    "vwap": 807.94
  },
  {
    "date": "2025-05-08",
    "open": 811.77,
    "high": 819.87,
    "low": 811.69,
    "close": 819.17,
    "volume": 550492,
    "trades": 2572,
    "vwap": 815.63
  },
  {
    "date": "2025-05-09",
    "open": 819.56,
    "high": 826.3,
    "low": 819.27,
    "close": 823.69,
    "volume": 432770,
    "trades": 1795,
    "vwap": 822.2
  },
  {
    "date": "2025-05-12",
    "open": 824.49,
    "high": 837.57,
    "low": 822.76,
    "close": 836.33,
    "volume": 706617,
    "trades": 949,
    "vwap": 830.29
  },
  {
    "date": "2025-05-13",
    "open": 836.17,
    "high": 838.01,
    "low": 829.18,
    "close": 830.96,
    "volume": 612594,
    "trades": 550,
    "vwap": 833.58
  },
  {
    "date": "2025-05-14",
    "open": 828.37,
    "high": 848.9,
    "low": 822.65,
    "close": 845.31,
    "volume": 974345,
    "trades": 1001,
    "vwap": 836.31
  },
  {
    "date": "2025-05-15",
    "open": 845.18,
    "high": 879.64,
    "low": 842.16,
    "close": 870.88,
    "volume": 358478,
    "trades": 859,
    "vwap": 859.46
  },
  {
    "date": "2025-05-16",
    "open": 873.69,
    "high": 874.54,
    "low": 860.19,
    "close": 862.94,
    "volume": 829238,
    "trades": 3498,
    "vwap": 867.84
  },
  {
    "date": "2025-05-19",
    "open": 866.11,
    "high": 870.12,
    "low": 859.97,
    "close": 866.67,
    "volume": 1010913,
    "trades": 911,
    "vwap": 865.72
  },
  {
    "date": "2025-05-20",
    "open": 865.26,
    "high": 883.59,
    "low": 862.27,
    "close": 881.22,
    "volume": 656633,
    "trades": 817,
    "vwap": 873.09
  },
  {
    "date": "2025-05-21",
    "open": 880.51,
    "high": 888.2,
    "low": 876.26,
    "close": 883.52,
    "volume": 507580,
    "trades": 697,
    "vwap": 882.12
  },
  {
    "date": "2025-05-22",
    "open": 883.35,
    "high": 890.25,
    "low": 877.11,
    "close": 886.63,
    "volume": 1474173,
    "trades": 3261,
    "vwap": 884.34
  },
  {
    "date": "2025-05-23",
    "open": 884.92,
    "high": 890.72,
    "low": 879.53,
    "close": 880.64,
    "volume": 662507,
    "trades": 1160,
    "vwap": 883.96
  },
  {
    "date": "2025-05-26",
    "open": 876.62,
    "high": 880.0,
    "low": 852.69,
    "close": 855.13,
    "volume": 1093147,
    "trades": 1214,
    "vwap": 866.11
  },
  {
    "date": "2025-05-27",
    "open": 850.17,
    "high": 850.73,
    "low": 836.37,
    "close": 843.01,
    "volume": 292657,
    "trades": 287,
    "vwap": 845.07
  },
  {
    "date": "2025-05-28",
    "open": 840.64,
    "high": 842.86,
    "low": 833.6,
    "close": 834.13,
    "volume": 874468,
    "trades": 4029,
    "vwap": 837.81
  },
  {
    "date": "2025-05-29",
    "open": 832.43,
    "high": 835.7,
    "low": 804.52,
    "close": 813.06,
    "volume": 962053,
    "trades": 1515,
    "vwap": 821.43
  },
  {
    "date": "2025-05-30",
    "open": 810.54,
    "high": 817.88,
    "low": 792.71,
    "close": 799.98,
    "volume": 499806,
    "trades": 1065,
    "vwap": 805.28
  },
  {
    "date": "2025-06-02",
    "open": 797.3,
    "high": 797.33,
    "low": 788.78,
    "close": 789.58,
    "volume": 1004291,
    "trades": 2341,
    "vwap": 793.25
  },
  {
    "date": "2025-06-03",
    "open": 789.65,
    "high": 789.8,
    "low": 774.79,
    "close": 777.15,
    "volume": 985398,
    "trades": 1091,
    "vwap": 782.85
  },
  {
    "date": "2025-06-04",
    "open": 777.8,
    "high": 796.43,
    "low": 775.93,
    "close": 793.28,
    "volume": 1127509,
    "trades": 1917,
    "vwap": 785.86
  },
  {
    "date": "2025-06-05",
    "open": 795.05,
    "high": 801.16,
    "low": 781.8,
    "close": 783.96,
    "volume": 809358,
    "trades": 831,
    "vwap": 790.49
  },
  {
    "date": "2025-06-06",
    "open": 789.61,
    "high": 806.18,
    "low": 788.18,
    "close": 804.48,
    "volume": 1114253,
    "trades": 1660,
    "vwap": 797.11
  },
  {
    "date": "2025-06-09",
    "open": 802.5,
    "high": 810.0,
    "low": 786.96,
    "close": 788.59,
    "volume": 737529,
    "trades": 1735,
    "vwap": 797.01
  },
  {
    "date": "2025-06-10",
    "open": 790.11,
    "high": 791.19,
    "low": 782.23,
    "close": 783.53,
    "volume": 717437,
    "trades": 942,
    "vwap": 786.77
  },
  {
    "date": "2025-06-11",
    "open": 780.99,
    "high": 785.39,
    "low": 777.42,
    "close": 785.19,
    "volume": 1225249,
    "trades": 4423,
    "vwap": 782.25
  },
  {
    "date": "2025-06-12",
    "open": 791.37,
    "high": 798.23,
    "low": 787.28,
    "close": 797.93,
    "volume": 1411636,
    "trades": 3878,
    "vwap": 793.7
  },
  {
    "date": "2025-06-13",
    "open": 801.2,
    "high": 815.21,
    "low": 800.64,
    "close": 805.65,
    "volume": 1047299,
    "trades": 1591,
    "vwap": 805.68
  },
  {
    "date": "2025-06-16",
    "open": 805.18,
    "high": 824.66,
    "low": 803.01,
    "close": 818.76,
    "volume": 895298,
    "trades": 823,
    "vwap": 812.9
  },
  {
    "date": "2025-06-17",
    "open": 820.99,
    "high": 836.18,
    "low": 819.19,
    "close": 825.56,
    "volume": 599970,
    "trades": 2553,
    "vwap": 825.48
  },
  {
    "date": "2025-06-18",
    "open": 829.75,
    "high": 831.85,
    "low": 827.22,
    "close": 831.6,
    "volume": 1031613,
    "trades": 868,
    "vwap": 830.1
  },
  {
    "date": "2025-06-19",
    "open": 829.9,
    "high": 830.5,
    "low": 814.53,
    "close": 820.89,
    "volume": 974068,
    "trades": 1319,
    "vwap": 823.96
  },
  {
    "date": "2025-06-20",
    "open": 818.6,
    "high": 822.06,
    "low": 813.64,
    "close": 820.73,
    "volume": 1045627,
    "trades": 2780,
    "vwap": 818.76
  },
  {
    "date": "2025-06-23",
    "open": 818.06,
    "high": 821.25,
    "low": 815.22,
    "close": 815.8,
    "volume": 639794,
    "trades": 3167,
    "vwap": 817.58
  },
  {
    "date": "2025-06-24",
    "open": 816.62,
    "high": 817.35,
    "low": 804.41,
    "close": 805.95,
    "volume": 701231,
    "trades": 887,
    "vwap": 811.08
  },
  {
    "date": "2025-06-25",
    "open": 803.1,
    "high": 803.78,
    "low": 792.36,
    "close": 799.18,
    "volume": 644993,
    "trades": 2021,
    "vwap": 799.6
  },
  {
    "date": "2025-06-26",
    "open": 797.93,
    "high": 805.51,
    "low": 795.18,
    "close": 804.07,
    "volume": 1123851,
    "trades": 3490,
    "vwap": 800.67
  },
  {
    "date": "2025-06-27",
    "open": 807.7,
    "high": 819.87,
    "low": 800.96,
    "close": 813.47,
    "volume": 1275231,
    "trades": 2730,
    "vwap": 810.5
  },
  {
    "date": "2025-06-30",
    "open": 812.87,
    "high": 817.32,
    "low": 800.18,
    "close": 805.01,
    "volume": 909656,
    "trades": 2584,
    "vwap": 808.85
  },
  {
    "date": "2025-07-01",
    "open": 801.55,
    "high": 802.62,
    "low": 772.47,
    "close": 778.76,
    "volume": 259626,
    "trades": 317,
    "vwap": 788.85
  },
  {
    "date": "2025-07-02",
    "open": 775.76,
    "high": 782.67,
    "low": 767.11,
    "close": 768.73,
    "volume": 0,
    "trades": 1,
    "vwap": 773.57
  },
  {
    "date": "2025-07-03",
    "open": 775.33,
    "high": 783.25,
    "low": 766.42,
    "close": 781.61,
    "volume": 782375,
    "trades": 989,
    "vwap": 776.65
  },
  {
    "date": "2025-07-04",
    "open": 780.13,
    "high": 790.48,
    "low": 771.49,
    "close": 787.86,
    "volume": 441527,
    "trades": 1711,
    "vwap": 782.49
  },
  {
    "date": "2025-07-07",
    "open": 789.03,
    "high": 794.34,
    "low": 786.94,
    "close": 787.16,
    "volume": 697424,
    "trades": 1064,
    "vwap": 789.37
  },
  {
    "date": "2025-07-08",
    "open": 792.23,
    "high": 814.64,
    "low": 791.93,
    "close": 810.57,
    "volume": 644147,
    "trades": 555,
    "vwap": 802.34
  },
  {
    "date": "2025-07-09",
    "open": 810.93,
    "high": 831.97,
    "low": 808.99,
    "close": 821.03,
    "volume": 304786,
    "trades": 374,
    "vwap": 818.23
  },
  {
    "date": "2025-07-10",
    "open": 825.91,
    "high": 831.21,
    "low": 813.65,
    "close": 820.61,
    "volume": 945628,
    "trades": 934,
    "vwap": 822.85
  },
  {
    "date": "2025-07-11",
    "open": 820.27,
    "high": 821.25,
    "low": 783.98,
    "close": 788.04,
    "volume": 835663,
    "trades": 1022,
    "vwap": 803.39
  },
  {
    "date": "2025-07-14",
    "open": 790.92,
    "high": 793.43,
    "low": 774.27,
    "close": 777.0,
    "volume": 852333,
    "trades": 1147,
    "vwap": 783.9
  },
  {
    "date": "2025-07-15",
    "open": 780.74,
    "high": 793.09,
    "low": 779.92,
    "close": 792.73,
    "volume": 633526,
    "trades": 2238,
    "vwap": 786.62
  },
  {
    "date": "2025-07-16",
    "open": 794.06,
    "high": 796.09,
    "low": 774.51,
    "close": 783.27,
    "volume": 594306,
    "trades": 500,
    "vwap": 786.98
  },
  {
    "date": "2025-07-17",
    "open": 788.2,
    "high": 802.21,
    "low": 780.58,
    "close": 796.38,
    "volume": 838310,
    "trades": 3917,
    "vwap": 791.84
  },
  {
    "date": "2025-07-18",
    "open": 797.18,
    "high": 798.76,
    "low": 789.42,
    "close": 795.35,
    "volume": 1477652,
    "trades": 1467,
    "vwap": 795.18
  },
  {
    "date": "2025-07-21",
    "open": 795.46,
    "high": 798.96,
    "low": 788.57,
    "close": 794.31,
    "volume": 1058689,
    "trades": 4321,
    "vwap": 794.32
  },
  {
    "date": "2025-07-22",
    "open": 797.66,
    "high": 800.78,
    "low": 777.94,
    "close": 784.1,
    "volume": 871277,
    "trades": 1043,
    "vwap": 790.12
  },
  {
    "date": "2025-07-23",
    "open": 785.13,
    "high": 785.23,
    "low": 773.45,
    "close": 776.53,
    "volume": 1012792,
    "trades": 1047,
    "vwap": 780.08
  },
  {
    "date": "2025-07-24",
    "open": 776.28,
    "high": 776.79,
    "low": 759.09,
    "close": 759.62,
    "volume": 1077944,
    "trades": 3678,
    "vwap": 767.95
  },
  {
    "date": "2025-07-25",
    "open": 759.19,
    "high": 760.19,
    "low": 757.85,
    "close": 759.14,
    "volume": 1165551,
    "trades": 3418,
    "vwap": 759.09
  },
  {
    "date": "2025-07-28",
    "open": 760.57,
    "high": 774.09,
    "low": 758.69,
    "close": 770.72,
    "volume": 702976,
    "trades": 1389,
    "vwap": 766.02
  },
  {
    "date": "2025-07-29",
    "open": 766.51,
    "high": 802.16,
    "low": 766.41,
    "close": 801.47,
    "volume": 951289,
    "trades": 1517,
    "vwap": 784.14
  },
  {
    "date": "2025-07-30",
    "open": 800.08,
    "high": 803.46,
    "low": 759.2,
    "close": 764.68,
    "volume": 962600,
    "trades": 1194,
    "vwap": 781.85
  },
  {
    "date": "2025-07-31",
    "open": 766.13,
    "high": 766.24,
    "low": 751.55,
    "close": 752.36,
    "volume": 1291919,
    "trades": 3254,
    "vwap": 759.07
  },
  {
    "date": "2025-08-01",
    "open": 751.08,
    "high": 755.32,
    "low": 733.0,
    "close": 737.35,
    "volume": 907481,
    "trades": 2853,
    "vwap": 744.18
  },
  {
    "date": "2025-08-04",
    "open": 740.48,
    "high": 740.5,
    "low": 731.16,
    "close": 735.94,
    "volume": 994130,
    "trades": 1040,
    "vwap": 737.02
  },
  {
    "date": "2025-08-05",
    "open": 737.87,
    "high": 764.55,
    "low": 733.7,
    "close": 763.39,
    "volume": 813707,
    "trades": 1039,
    "vwap": 749.88
  },
  {
    "date": "2025-08-06",
    "open": 768.02,
    "high": 775.11,
    "low": 758.96,
    "close": 762.47,
    "volume": 346476,
    "trades": 546,
    "vwap": 766.14
  },
  {
    "date": "2025-08-07",
    "open": 765.17,
    "high": 776.42,
    "low": 758.23,
    "close": 772.7,
    "volume": 816467,
    "trades": 1229,
    "vwap": 768.13
  },
  {
    "date": "2025-08-08",
    "open": 775.41,
    "high": 793.29,
    "low": 768.99,
    "close": 790.15,
    "volume": 685830,
    "trades": 581,
    "vwap": 781.96
  },
  {
    "date": "2025-08-11",
    "open": 788.34,
    "high": 791.02,
    "low": 757.35,
    "close": 759.9,
    "volume": 605103,
    "trades": 929,
    "vwap": 774.15
  },
  {
    "date": "2025-08-12",
    "open": 758.78,
    "high": 770.53,
    "low": 757.99,
    "close": 767.68,
    "volume": 1002170,
    "trades": 1739,
    "vwap": 763.75
  },
  {
    "date": "2025-08-13",
    "open": 764.15,
    "high": 765.32,
    "low": 758.16,
    "close": 760.35,
    "volume": 616003,
    "trades": 2933,
    "vwap": 762.0
  },
  {
    "date": "2025-08-14",
    "open": 757.36,
    "high": 759.48,
    "low": 746.66,
    "close": 748.44,
    "volume": 1099463,
    "trades": 1068,
    "vwap": 752.98
  },
  {
    "date": "2025-08-15",
    "open": 745.84,
    "high": 751.73,
    "low": 739.33,
    "close": 745.18,
    "volume": 1350987,
    "trades": 1927,
    "vwap": 745.52
  },
  {
    "date": "2025-08-18",
    "open": 745.34,
    "high": 760.4,
    "low": 740.47,
    "close": 760.11,
    "volume": 1316949,
    "trades": 2117,
    "vwap": 751.58
  },
  {
    "date": "2025-08-19",
    "open": 758.62,
    "high": 760.3,
    "low": 745.6,
    "close": 747.67,
    "volume": 1973529,
    "trades": 2663,
    "vwap": 753.05
  },
  {
    "date": "2025-08-20",
    "open": 750.04,
    "high": 760.78,
    "low": 746.78,
    "close": 758.53,
    "volume": 860475,
    "trades": 2306,
    "vwap": 754.03
  },
  {
    "date": "2025-08-21",
    "open": 758.31,
    "high": 762.23,
    "low": 736.78,
    "close": 745.43,
    "volume": 1415545,
    "trades": 1274,
    "vwap": 750.69
  },
  {
    "date": "2025-08-22",
    "open": 747.73,
    "high": 748.32,
    "low": 743.05,
    "close": 745.61,
    "volume": 823831,
    "trades": 1222,
    "vwap": 746.18
  },
  {
    "date": "2025-08-25",
    "open": 748.82,
    "high": 769.99,
    "low": 748.22,
    "close": 769.69,
    "volume": 1519706,
    "trades": 3542,
    "vwap": 759.18
  },
  {
    "date": "2025-08-26",
    "open": 777.09,
    "high": 784.26,
    "low": 772.74,
    "close": 780.31,
    "volume": 851220,
    "trades": 2371,
    "vwap": 778.6
  },
  {
    "date": "2025-08-27",
    "open": 779.02,
    "high": 781.6,
    "low": 759.26,
    "close": 759.44,
    "volume": 1026923,
    "trades": 2029,
    "vwap": 769.83
  },
  {
    "date": "2025-08-28",
    "open": 760.77,
    "high": 784.59,
    "low": 757.76,
    "close": 783.87,
    "volume": 989581,
    "trades": 1856,
    "vwap": 771.75
  },
  {
    "date": "2025-08-29",
    "open": 783.26,
    "high": 786.01,
    "low": 760.95,
    "close": 761.06,
    "volume": 695081,
    "trades": 632,
    "vwap": 772.82
  },
  {
    "date": "2025-09-01",
    "open": 764.45,
    "high": 775.5,
    "low": 755.89,
    "close": 770.31,
    "volume": 434384,
    "trades": 571,
    "vwap": 766.54
  },
  {
    "date": "2025-09-02",
    "open": 772.73,
    "high": 773.48,
    "low": 759.84,
    "close": 765.37,
    "volume": 1203301,
    "trades": 4375,
    "vwap": 767.85
  },
  {
    "date": "2025-09-03",
    "open": 765.61,
    "high": 766.16,
    "low": 755.26,
    "close": 759.86,
    "volume": 255490,
    "trades": 387,
    "vwap": 761.72
  },
  {
    "date": "2025-09-04",
    "open": 762.36,
    "high": 762.96,
    "low": 759.75,
    "close": 760.86,
    "volume": 549144,
    "trades": 1345,
    "vwap": 761.48
  },
  {
    "date": "2025-09-05",
    "open": 759.71,
    "high": 763.88,
    "low": 746.38,
    "close": 751.01,
    "volume": 1088590,
    "trades": 2301,
    "vwap": 755.24
  },
  {
    "date": "2025-09-08",
    "open": 750.94,
    "high": 753.21,
    "low": 745.39,
    "close": 752.15,
    "volume": 786282,
    "trades": 906,
    "vwap": 750.42
  },
  {
    "date": "2025-09-09",
    "open": 746.36,
    "high": 747.47,
    "low": 729.34,
    "close": 731.64,
    "volume": 1070032,
    "trades": 4229,
    "vwap": 738.7
  },
  {
    "date": "2025-09-10",
    "open": 731.94,
    "high": 745.06,
    "low": 730.46,
    "close": 743.5,
    "volume": 804328,
    "trades": 758,
    "vwap": 737.74
  },
  {
    "date": "2025-09-11",
    "open": 739.46,
    "high": 741.17,
    "low": 726.89,
    "close": 730.04,
    "volume": 1183789,
    "trades": 1539,
    "vwap": 734.39
  },
  {
    "date": "2025-09-12",
    "open": 729.7,
    "high": 731.67,
    "low": 697.21,
    "close": 698.87,
    "volume": 1012063,
    "trades": 3588,
    "vwap": 714.36
  },
  {
    "date": "2025-09-15",
    "open": 704.0,
    "high": 709.28,
    "low": 700.98,
    "close": 707.19,
    "volume": 1157399,
    "trades": 1547,
    "vwap": 705.36
  },
  {
    "date": "2025-09-16",
    "open": 705.92,
    "high": 708.7,
    "low": 699.35,
    "close": 704.14,
    "volume": 958696,
    "trades": 1519,
    "vwap": 704.53
  },
  {
    "date": "2025-09-17",
    "open": 703.73,
    "high": 714.84,
    "low": 697.73,
    "close": 712.82,
    "volume": 1437497,
    "trades": 2299,
    "vwap": 707.28
  },
  {
    "date": "2025-09-18",
    "open": 714.31,
    "high": 715.56,
    "low": 693.53,
    "close": 700.08,
    "volume": 883740,
    "trades": 929,
    "vwap": 705.87
  },
  {
    "date": "2025-09-19",
    "open": 698.61,
    "high": 701.9,
    "low": 677.01,
    "close": 680.12,
    "volume": 730091,
    "trades": 739,
    "vwap": 689.41
  },
  {
    "date": "2025-09-22",
    "open": 683.46,
    "high": 689.99,
    "low": 677.16,
    "close": 684.02,
    "volume": 756558,
    "trades": 801,
    "vwap": 683.66
  },
  {
    "date": "2025-09-23",
    "open": 682.65,
    "high": 684.4,
    "low": 671.8,
    "close": 676.0,
    "volume": 957442,
    "trades": 3845,
    "vwap": 678.71
  },
  {
    "date": "2025-09-24",
    "open": 678.27,
    "high": 683.41,
    "low": 674.43,
    "close": 677.55,
    "volume": 798975,
    "trades": 2428,
    "vwap": 678.41
  },
  {
    "date": "2025-09-25",
    "open": 673.95,
    "high": 674.07,
    "low": 673.59,
    "close": 673.85,
    "volume": 1008859,
    "trades": 1113,
    "vwap": 673.87
  },
  {
    "date": "2025-09-26",
    "open": 671.42,
    "high": 679.65,
    "low": 670.47,
    "close": 678.26,
    "volume": 1017213,
    "trades": 2150,
    "vwap": 674.95
  },
  {
    "date": "2025-09-29",
    "open": 680.1,
    "high": 706.9,
    "low": 678.21,
    "close": 704.58,
    "volume": 704500,
    "trades": 718,
    "vwap": 692.45
  },
  {
    "date": "2025-09-30",
    "open": 701.83,
    "high": 704.09,
    "low": 677.97,
    "close": 679.34,
    "volume": 878613,
    "trades": 1007,
    "vwap": 690.81
  },
  {
    "date": "2025-10-01",
    "open": 678.22,
    "high": 702.81,
    "low": 677.94,
    "close": 693.99,
    "volume": 855148,
    "trades": 1896,
    "vwap": 688.24
  },
  {
    "date": "2025-10-02",
    "open": 691.65,
    "high": 692.6,
    "low": 683.89,
    "close": 685.53,
    "volume": 1163265,
    "trades": 4406,
    "vwap": 688.42
  },
  {
    "date": "2025-10-03",
    "open": 684.92,
    "high": 688.1,
    "low": 669.4,
    "close": 675.89,
    "volume": 1074937,
    "trades": 1051,
    "vwap": 679.58
  },
  {
    "date": "2025-10-06",
    "open": 675.66,
    "high": 681.34,
    "low": 672.65,
    "close": 675.53,
    "volume": 1066250,
    "trades": 3280,
    "vwap": 676.29
  },
  {
    "date": "2025-10-07",
    "open": 674.01,
    "high": 682.79,
    "low": 670.46,
    "close": 681.37,
    "volume": 975217,
    "trades": 1093,
    "vwap": 677.16
  },
  {
    "date": "2025-10-08",
    "open": 677.88,
    "high": 678.94,
    "low": 659.93,
    "close": 666.86,
    "volume": 647084,
    "trades": 1822,
    "vwap": 670.9
  },
  {
    "date": "2025-10-09",
    "open": 666.26,
    "high": 672.25,
    "low": 664.88,
    "close": 668.77,
    "volume": 135979,
    "trades": 357,
    "vwap": 668.04
  },
  {
    "date": "2025-10-10",
    "open": 667.9,
    "high": 672.25,
    "low": 664.2,
    "close": 667.28,
    "volume": 646775,
    "trades": 1421,
    "vwap": 667.91
  },
  {
    "date": "2025-10-13",
    "open": 664.89,
    "high": 665.23,
    "low": 649.63,
    "close": 654.17,
    "volume": 1092892,
    "trades": 3291,
    "vwap": 658.48
  },
  {
    "date": "2025-10-14",
    "open": 654.91,
    "high": 666.94,
    "low": 653.14,
    "close": 665.21,
    "volume": 797684,
    "trades": 693,
    "vwap": 660.05
  },
  {
    "date": "2025-10-15",
    "open": 665.27,
    "high": 667.93,
    "low": 649.14,
    "close": 655.15,
    "volume": 841328,
    "trades": 1186,
    "vwap": 659.37
  },
  {
    "date": "2025-10-16",
    "open": 657.96,
    "high": 658.15,
    "low": 635.67,
    "close": 636.63,
    "volume": 664432,
    "trades": 1085,
    "vwap": 647.1
  },
  {
    "date": "2025-10-17",
    "open": 634.3,
    "high": 635.76,
    "low": 625.5,
    "close": 632.5,
    "volume": 16549,
    "trades": 14,
    "vwap": 632.02
  },
  {
    "date": "2025-10-20",
    "open": 632.97,
    "high": 634.52,
    "low": 620.55,
    "close": 621.71,
    "volume": 784687,
    "trades": 1886,
    "vwap": 627.44
  },
  {
    "date": "2025-10-21",
    "open": 620.8,
    "high": 622.23,
    "low": 619.47,
    "close": 620.14,
    "volume": 985329,
    "trades": 1000,
    "vwap": 620.66
  },
  {
    "date": "2025-10-22",
    "open": 618.95,
    "high": 639.06,
    "low": 618.89,
    "close": 636.34,
    "volume": 1566882,
    "trades": 2254,
    "vwap": 628.31
  },
  {
    "date": "2025-10-23",
    "open": 638.58,
    "high": 640.93,
    "low": 632.86,
    "close": 640.54,
    "volume": 1141806,
    "trades": 2150,
    "vwap": 638.23
  },
  {
    "date": "2025-10-24",
    "open": 640.11,
    "high": 643.32,
    "low": 620.05,
    "close": 625.46,
    "volume": 1173734,
    "trades": 3155,
    "vwap": 632.23
  },
  {
    "date": "2025-10-27",
    "open": 628.72,
    "high": 642.93,
    "low": 623.18,
    "close": 640.59,
    "volume": 1072629,
    "trades": 1109,
    "vwap": 633.86
  },
  {
    "date": "2025-10-28",
    "open": 636.21,
    "high": 646.57,
    "low": 635.6,
    "close": 640.75,
    "volume": 878393,
    "trades": 938,
    "vwap": 639.78
  },
  {
    "date": "2025-10-29",
    "open": 643.12,
    "high": 646.35,
    "low": 639.84,
    "close": 645.24,
    "volume": 938355,
    "trades": 1010,
    "vwap": 643.64
  },
  {
    "date": "2025-10-30",
    "open": 643.81,
    "high": 646.24,
    "low": 633.03,
    "close": 634.99,
    "volume": 723803,
    "trades": 1422,
    "vwap": 639.52
  },
  {
    "date": "2025-10-31",
    "open": 631.72,
    "high": 638.94,
    "low": 611.42,
    "close": 619.88,
    "volume": 1199067,
    "trades": 2982,
    "vwap": 625.49
  },
  {
    "date": "2025-11-03",
    "open": 616.12,
    "high": 620.36,
    "low": 613.44,
    "close": 619.06,
    "volume": 900842,
    "trades": 1484,
    "vwap": 617.25
  },
  {
    "date": "2025-11-04",
    "open": 619.36,
    "high": 635.01,
    "low": 617.08,
    "close": 633.74,
    "volume": 616572,
    "trades": 1475,
    "vwap": 626.3
  },
  {
    "date": "2025-11-05",
    "open": 634.67,
    "high": 635.33,
    "low": 622.05,
    "close": 623.31,
    "volume": 1062469,
    "trades": 1388,
    "vwap": 628.84
  },
  {
    "date": "2025-11-06",
    "open": 621.14,
    "high": 649.68,
    "low": 620.96,
    "close": 643.86,
    "volume": 538617,
    "trades": 721,
    "vwap": 633.91
  },
  {
    "date": "2025-11-07",
    "open": 642.93,
    "high": 646.59,
    "low": 636.18,
    "close": 637.84,
    "volume": 1077782,
    "trades": 3821,
    "vwap": 640.89
  },
  {
    "date": "2025-11-10",
    "open": 637.32,
    "high": 640.19,
    "low": 619.71,
    "close": 626.97,
    "volume": 790036,
    "trades": 1057,
    "vwap": 631.05
  },
  {
    "date": "2025-11-11",
    "open": 625.13,
    "high": 636.64,
    "low": 622.35,
    "close": 622.57,
    "volume": 1372861,
    "trades": 2878,
    "vwap": 626.67
  },
  {
    "date": "2025-11-12",
    "open": 622.82,
    "high": 629.11,
    "low": 614.4,
    "close": 617.28,
    "volume": 782274,
    "trades": 876,
    "vwap": 620.9
  },
  {
    "date": "2025-11-13",
    "open": 616.75,
    "high": 617.43,
    "low": 612.62,
    "close": 617.35,
    "volume": 675884,
    "trades": 728,
    "vwap": 616.04
  },
  {
    "date": "2025-11-14",
    "open": 619.64,
    "high": 633.06,
    "low": 619.22,
    "close": 629.41,
    "volume": 884266,
    "trades": 2422,
    "vwap": 625.33
  },
  {
    "date": "2025-11-17",
    "open": 630.43,
    "high": 630.97,
    "low": 613.5,
    "close": 618.5,
    "volume": 364807,
    "trades": 549,
    "vwap": 623.35
  },
  {
    "date": "2025-11-18",
    "open": 616.58,
    "high": 617.17,
    "low": 612.13,
    "close": 616.7,
    "volume": 878927,
    "trades": 1046,
    "vwap": 615.65
  },
  {
    "date": "2025-11-19",
    "open": 617.29,
    "high": 626.73,
    "low": 616.52,
    "close": 622.91,
    "volume": 781493,
    "trades": 2520,
    "vwap": 620.86
  },
  {
    "date": "2025-11-20",
    "open": 622.09,
    "high": 624.04,
    "low": 609.49,
    "close": 615.94,
    "volume": 831604,
    "trades": 1091,
    "vwap": 617.89
  },
  {
    "date": "2025-11-21",
    "open": 619.23,
    "high": 632.52,
    "low": 617.05,
    "close": 631.22,
    "volume": 989174,
    "trades": 1194,
    "vwap": 625.01
  },
  {
    "date": "2025-11-24",
    "open": 630.35,
    "high": 637.03,
    "low": 621.68,
    "close": 631.7,
    "volume": 1163216,
    "trades": 1454,
    "vwap": 630.19
  },
  {
    "date": "2025-11-25",
    "open": 630.83,
    "high": 647.41,
    "low": 629.95,
    "close": 647.31,
    "volume": 353909,
    "trades": 483,
    "vwap": 638.87
  },
  {
    "date": "2025-11-26",
    "open": 646.7,
    "high": 649.47,
    "low": 645.35,
    "close": 646.4,
    "volume": 515639,
    "trades": 671,
    "vwap": 646.98
  },
  {
    "date": "2025-11-27",
    "open": 646.1,
    "high": 650.47,
    "low": 645.33,
    "close": 649.36,
    "volume": 1505409,
    "trades": 1978,
    "vwap": 647.82
  },
  {
    "date": "2025-11-28",
    "open": 650.83,
    "high": 662.98,
    "low": 647.29,
    "close": 661.54,
    "volume": 783813,
    "trades": 2147,
    "vwap": 655.66
  },
  {
    "date": "2025-12-01",
    "open": 661.46,
    "high": 662.4,
    "low": 643.86,
    "close": 643.92,
    "volume": 665736,
    "trades": 723,
    "vwap": 652.91
  },
  {
    "date": "2025-12-02",
    "open": 642.9,
    "high": 647.53,
    "low": 634.78,
    "close": 637.09,
    "volume": 1012889,
    "trades": 1132,
    "vwap": 640.57
  },
  {
    "date": "2025-12-03",
    "open": 634.5,
    "high": 647.85,
    "low": 634.27,
    "close": 638.59,
    "volume": 737051,
    "trades": 857,
    "vwap": 638.8
  },
  {
    "date": "2025-12-04",
    "open": 638.73,
    "high": 646.57,
    "low": 638.01,
    "close": 640.9,
    "volume": 925021,
    "trades": 2620,
    "vwap": 641.05
  },
  {
    "date": "2025-12-05",
    "open": 644.39,
    "high": 647.54,
    "low": 635.5,
    "close": 643.82,
    "volume": 1130409,
    "trades": 2990,
    "vwap": 642.81
  },
  {
    "date": "2025-12-08",
    "open": 642.9,
    "high": 646.6,
    "low": 641.45,
    "close": 645.27,
    "volume": 790915,
    "trades": 1972,
    "vwap": 644.05
  },
  {
    "date": "2025-12-09",
    "open": 644.68,
    "high": 648.99,
    "low": 638.49,
    "close": 640.45,
    "volume": 878305,
    "trades": 3992,
    "vwap": 643.15
  },
  {
    "date": "2025-12-10",
    "open": 640.43,
    "high": 658.12,
    "low": 636.93,
    "close": 654.14,
    "volume": 717195,
    "trades": 1207,
    "vwap": 647.4
  },
  {
    "date": "2025-12-11",
    "open": 650.39,
    "high": 654.96,
    "low": 635.78,
    "close": 637.77,
    "volume": 1457977,
    "trades": 2685,
    "vwap": 644.73
  },
  {
    "date": "2025-12-12",
    "open": 635.97,
    "high": 652.45,
    "low": 632.54,
    "close": 652.21,
    "volume": 634328,
    "trades": 2402,
    "vwap": 643.29
  },
  {
    "date": "2025-12-15",
    "open": 651.46,
    "high": 655.22,
    "low": 635.84,
    "close": 645.87,
    "volume": 1026042,
    "trades": 1111,
    "vwap": 647.1
  },
  {
    "date": "2025-12-16",
    "open": 646.32,
    "high": 673.06,
    "low": 642.8,
    "close": 670.04,
    "volume": 1380343,
    "trades": 1714,
    "vwap": 658.05
  },
  {
    "date": "2025-12-17",
    "open": 669.89,
    "high": 671.61,
    "low": 658.06,
    "close": 663.86,
    "volume": 1082050,
    "trades": 1492,
    "vwap": 665.86
  },
  {
    "date": "2025-12-18",
    "open": 666.09,
    "high": 674.29,
    "low": 661.64,
    "close": 668.0,
    "volume": 678461,
    "trades": 720,
    "vwap": 667.51
  },
  {
    "date": "2025-12-19",
    "open": 668.19,
    "high": 673.04,
    "low": 662.34,
    "close": 663.87,
    "volume": 948540,
    "trades": 1544,
    "vwap": 666.86
  },
  {
    "date": "2025-12-22",
    "open": 662.71,
    "high": 664.93,
    "low": 651.56,
    "close": 652.33,
    "volume": 984400,
    "trades": 1605,
    "vwap": 657.88
  },
  {
    "date": "2025-12-23",
    "open": 654.28,
    "high": 671.99,
    "low": 650.82,
    "close": 668.53,
    "volume": 874134,
    "trades": 840,
    "vwap": 661.4
  },
  {
    "date": "2025-12-24",
    "open": 669.48,
    "high": 684.13,
    "low": 668.67,
    "close": 681.78,
    "volume": 997907,
    "trades": 2756,
    "vwap": 676.02
  },
  {
    "date": "2025-12-25",
    "open": 683.07,
    "high": 694.84,
    "low": 676.25,
    "close": 693.74,
    "volume": 383731,
    "trades": 319,
    "vwap": 686.98
  },
  {
    "date": "2025-12-26",
    "open": 696.68,
    "high": 704.45,
    "low": 681.11,
    "close": 683.39,
    "volume": 554161,
    "trades": 869,
    "vwap": 691.41
  },
  {
    "date": "2025-12-29",
    "open": 683.5,
    "high": 684.6,
    "low": 670.47,
    "close": 673.01,
    "volume": 532501,
    "trades": 849,
    "vwap": 677.9
  },
  {
    "date": "2025-12-30",
    "open": 672.27,
    "high": 675.99,
    "low": 667.57,
    "close": 673.78,
    "volume": 740634,
    "trades": 853,
    "vwap": 672.4
  },
  {
    "date": "2025-12-31",
    "open": 674.45,
    "high": 675.19,
    "low": 660.4,
    "close": 663.49,
    "volume": 1312969,
    "trades": 2431,
    "vwap": 668.38
  },
  {
    "date": "2026-01-01",
    "open": 663.02,
    "high": 680.34,
    "low": 658.73,
    "close": 677.53,
    "volume": 1225563,
    "trades": 1957,
    "vwap": 669.91
  },
  {
    "date": "2026-01-02",
    "open": 677.17,
    "high": 680.03,
    "low": 672.61,
    "close": 675.7,
    "volume": 1385382,
    "trades": 3744,
    "vwap": 676.38
  },
  {
    "date": "2026-01-05",
    "open": 677.69,
    "high": 678.84,
    "low": 671.6,
    "close": 674.93,
    "volume": 1189768,
    "trades": 1093,
    "vwap": 675.77
  },
  {
    "date": "2026-01-06",
    "open": 675.11,
    "high": 677.06,
    "low": 668.55,
    "close": 668.92,
    "volume": 1228032,
    "trades": 1147,
    "vwap": 672.41
  },
  {
    "date": "2026-01-07",
    "open": 667.29,
    "high": 687.09,
    "low": 665.15,
    "close": 677.44,
    "volume": 683334,
    "trades": 2009,
    "vwap": 674.24
  },
  {
    "date": "2026-01-08",
    "open": 678.93,
    "high": 689.83,
    "low": 675.72,
    "close": 685.58,
    "volume": 1010532,
    "trades": 4010,
    "vwap": 682.51
  },
  {
    "date": "2026-01-09",
    "open": 682.69,
    "high": 695.96,
    "low": 679.28,
    "close": 691.69,
    "volume": 1126467,
    "trades": 1768,
    "vwap": 687.41
  },
  {
    "date": "2026-01-12",
    "open": 691.36,
    "high": 696.03,
    "low": 673.55,
    "close": 682.41,
    "volume": 374938,
    "trades": 516,
    "vwap": 685.84
  },
  {
    "date": "2026-01-13",
    "open": 682.36,
    "high": 690.57,
    "low": 678.54,
    "close": 688.28,
    "volume": 1061618,
    "trades": 2073,
    "vwap": 684.94
  },
  {
    "date": "2026-01-14",
    "open": 688.92,
    "high": 695.05,
    "low": 688.2,
    "close": 690.9,
    "volume": 1135608,
    "trades": 2846,
    "vwap": 690.77
  },
  {
    "date": "2026-01-15",
    "open": 683.37,
    "high": 686.16,
    "low": 681.28,
    "close": 684.87,
    "volume": 490201,
    "trades": 640,
    "vwap": 683.92
  },
  {
    "date": "2026-01-16",
    "open": 685.99,
    "high": 688.87,
    "low": 677.98,
    "close": 680.77,
    "volume": 1502022,
    "trades": 1294,
    "vwap": 683.4
  },
  {
    "date": "2026-01-19",
    "open": 678.34,
    "high": 695.82,
    "low": 670.48,
    "close": 690.59,
    "volume": 873848,
    "trades": 835,
    "vwap": 683.81
  },
  {
    "date": "2026-01-20",
    "open": 689.75,
    "high": 712.96,
    "low": 686.28,
    "close": 705.03,
    "volume": 640208,
    "trades": 568,
    "vwap": 698.5
  },
  {
    "date": "2026-01-21",
    "open": 707.25,
    "high": 715.37,
    "low": 706.78,
    "close": 711.1,
    "volume": 481651,
    "trades": 450,
    "vwap": 710.13
  },
  {
    "date": "2026-01-22",
    "open": 713.33,
    "high": 713.51,
    "low": 706.6,
    "close": 709.47,
    "volume": 1438248,
    "trades": 3542,
    "vwap": 710.73
  },
  {
    "date": "2026-01-23",
    "open": 708.16,
    "high": 712.41,
    "low": 699.74,
    "close": 701.16,
    "volume": 1133180,
    "trades": 1066,
    "vwap": 705.37
  },
  {
    "date": "2026-01-26",
    "open": 699.89,
    "high": 703.17,
    "low": 695.31,
    "close": 703.06,
    "volume": 707701,
    "trades": 671,
    "vwap": 700.36
  },
  {
    "date": "2026-01-27",
    "open": 703.45,
    "high": 704.24,
    "low": 695.65,
    "close": 697.75,
    "volume": 644401,
    "trades": 747,
    "vwap": 700.27
  },
  {
    "date": "2026-01-28",
    "open": 698.68,
    "high": 709.89,
    "low": 694.41,
    "close": 696.84,
    "volume": 868769,
    "trades": 872,
    "vwap": 699.95
  },
  {
    "date": "2026-01-29",
    "open": 697.67,
    "high": 702.58,
    "low": 692.77,
    "close": 699.63,
    "volume": 915953,
    "trades": 2429,
    "vwap": 698.16
  },
  {
    "date": "2026-01-30",
    "open": 702.72,
    "high": 734.67,
    "low": 701.35,
    "close": 727.97,
    "volume": 1156677,
    "trades": 1141,
    "vwap": 716.68
  },
  {
    "date": "2026-02-02",
    "open": 728.42,
    "high": 744.34,
    "low": 725.55,
    "close": 736.17,
    "volume": 853098,
    "trades": 1003,
    "vwap": 733.62
  },
  {
    "date": "2026-02-03",
    "open": 735.12,
    "high": 747.6,
    "low": 729.44,
    "close": 739.16,
    "volume": 1142356,
    "trades": 1289,
    "vwap": 737.83
  },
  {
    "date": "2026-02-04",
    "open": 734.98,
    "high": 740.91,
    "low": 731.55,
    "close": 738.95,
    "volume": 874641,
    "trades": 960,
    "vwap": 736.6
  },
  {
    "date": "2026-02-05",
    "open": 743.36,
    "high": 751.96,
    "low": 733.56,
    "close": 741.86,
    "volume": 418388,
    "trades": 429,
    "vwap": 742.69
  },
  {
    "date": "2026-02-06",
    "open": 738.73,
    "high": 739.12,
    "low": 734.5,
    "close": 734.84,
    "volume": 920890,
    "trades": 1000,
    "vwap": 736.8
  },
  {
    "date": "2026-02-09",
    "open": 730.08,
    "high": 745.93,
    "low": 729.14,
    "close": 739.68,
    "volume": 815962,
    "trades": 727,
    "vwap": 736.21
  },
  {
    "date": "2026-02-10",
    "open": 741.17,
    "high": 753.3,
    "low": 737.82,
    "close": 747.31,
    "volume": 466954,
    "trades": 861,
    "vwap": 744.9
  },
  {
    "date": "2026-02-11",
    "open": 745.2,
    "high": 759.48,
    "low": 738.36,
    "close": 754.84,
    "volume": 1234947,
    "trades": 1637,
    "vwap": 749.47
  },
  {
    "date": "2026-02-12",
    "open": 758.49,
    "high": 788.15,
    "low": 758.14,
    "close": 781.19,
    "volume": 466822,
    "trades": 946,
    "vwap": 771.49
  },
  {
    "date": "2026-02-13",
    "open": 783.76,
    "high": 810.81,
    "low": 776.83,
    "close": 809.22,
    "volume": 1736994,
    "trades": 2748,
    "vwap": 795.16
  },
  {
    "date": "2026-02-16",
    "open": 806.73,
    "high": 810.29,
    "low": 794.39,
    "close": 800.02,
    "volume": 786768,
    "trades": 905,
    "vwap": 802.86
  },
  {
    "date": "2026-02-17",
    "open": 802.01,
    "high": 813.78,
    "low": 799.22,
    "close": 810.15,
    "volume": 788956,
    "trades": 842,
    "vwap": 806.29
  },
  {
    "date": "2026-02-18",
    "open": 811.89,
    "high": 829.17,
    "low": 809.61,
    "close": 826.16,
    "volume": 885423,
    "trades": 3303,
    "vwap": 819.21
  },
  {
    "date": "2026-02-19",
    "open": 827.88,
    "high": 829.28,
    "low": 804.91,
    "close": 806.01,
    "volume": 713054,
    "trades": 632,
    "vwap": 817.02
  },
  {
    "date": "2026-02-20",
    "open": 807.88,
    "high": 810.89,
    "low": 805.0,
    "close": 809.37,
    "volume": 1010773,
    "trades": 1417,
    "vwap": 808.28
  },
  {
    "date": "2026-02-23",
    "open": 812.02,
    "high": 821.76,
    "low": 810.38,
    "close": 821.16,
    "volume": 635843,
    "trades": 1204,
    "vwap": 816.33
  },
  {
    "date": "2026-02-24",
    "open": 819.53,
    "high": 828.45,
    "low": 812.75,
    "close": 813.13,
    "volume": 1040198,
    "trades": 2035,
    "vwap": 818.47
  },
  {
    "date": "2026-02-25",
    "open": 811.91,
    "high": 822.15,
    "low": 800.34,
    "close": 820.06,
    "volume": 1291840,
    "trades": 4646,
    "vwap": 813.61
  },
  {
    "date": "2026-02-26",
    "open": 817.53,
    "high": 829.73,
    "low": 816.39,
    "close": 826.6,
    "volume": 980688,
    "trades": 2910,
    "vwap": 822.56
  },
  {
    "date": "2026-02-27",
    "open": 829.63,
    "high": 844.8,
    "low": 828.28,
    "close": 835.36,
    "volume": 146107,
    "trades": 247,
    "vwap": 834.51
  }
]